[{"NomBarreau":"GRASSE","avNom":"ACHIARDY","avPrenom":"Elodie","cbRaisonSociale":"ACHIARDY ELODIE","cbSiretSiren":"519125140","cbAdresse1":"8-10 Cours du 11 novembre","cbAdresse2":"Le Central Plaza","cbCp":"6800","cbVille":"CAGNES SUR MER","spLibelle1":"","spLibelle2":"","acDateSerment":"","coordinates":[7.1497131,43.6616545]},{"NomBarreau":"GRASSE","avNom":"ADDAD","avPrenom":"Mekia Noura","cbRaisonSociale":"ADDAD MEKIA NOURA","cbSiretSiren":"809249394","cbAdresse1":"6 avenue Cyrille Besset","cbAdresse2":"Le Virginia II","cbCp":"6800","cbVille":"CAGNES SUR MER","spLibelle1":"","spLibelle2":"","acDateSerment":"","coordinates":[7.1627036,43.6589848]},{"NomBarreau":"GRASSE","avNom":"CARRION-TAMIOTTI","avPrenom":"Celine","cbRaisonSociale":"CARRION-TAMIOTTI - TERESI","cbSiretSiren":"522671437","cbAdresse1":"1 rue Modigliani","cbAdresse2":"","cbCp":"6800","cbVille":"CAGNES SUR MER","spLibelle1":"","spLibelle2":"","acDateSerment":"","coordinates":[7.1521049,43.6651327]},{"NomBarreau":"GRASSE","avNom":"DAN","avPrenom":"Philippe","cbRaisonSociale":"DELAGE - DAN - LARRIBEAU - RENAUDOT","cbSiretSiren":"444784045","cbAdresse1":"19 avenue Auguste Renoir","cbAdresse2":"","cbCp":"6800","cbVille":"CAGNES SUR MER","spLibelle1":"","spLibelle2":"","acDateSerment":"","coordinates":[7.1537511,43.6651539]},{"NomBarreau":"GRASSE","avNom":"DE ANDRADE","avPrenom":"NASTASIA","cbRaisonSociale":"DE ANDRADE NASTASIA","cbSiretSiren":"948015417","cbAdresse1":"19 avenue Auguste Renoir","cbAdresse2":"Le Sainte Luce","cbCp":"6800","cbVille":"CAGNES SUR MER","spLibelle1":"","spLibelle2":"","acDateSerment":"","coordinates":[7.1537511,43.6651539]},{"NomBarreau":"GRASSE","avNom":"DELAS","avPrenom":"Audrey","cbRaisonSociale":"DELAS AUDREY","cbSiretSiren":"809060395","cbAdresse1":"80 avenue de Nice","cbAdresse2":"","cbCp":"6800","cbVille":"CAGNES SUR MER","spLibelle1":"","spLibelle2":"","acDateSerment":"","coordinates":[7.1773215,43.6605767]},{"NomBarreau":"GRASSE","avNom":"DI CROSTA","avPrenom":"Magali","cbRaisonSociale":"DI CROSTA MAGALI","cbSiretSiren":"539912162","cbAdresse1":"8 place de Gaulle","cbAdresse2":"Le Paris","cbCp":"6800","cbVille":"CAGNES SUR MER","spLibelle1":"","spLibelle2":"","acDateSerment":"","coordinates":[7.1503884,43.6639415]},{"NomBarreau":"GRASSE","avNom":"DUFET","avPrenom":"Julien","cbRaisonSociale":"DFT AVOCATS","cbSiretSiren":"914971577","cbAdresse1":"10 Avenue de Nice","cbAdresse2":"Le Deauville","cbCp":"6800","cbVille":"CAGNES SUR MER","spLibelle1":"","spLibelle2":"","acDateSerment":"","coordinates":[7.152997,43.6554371]},{"NomBarreau":"GRASSE","avNom":"DUPETIT-EVRARD","avPrenom":"Diane","cbRaisonSociale":"DUPETIT-EVRARD DIANE","cbSiretSiren":"448728758","cbAdresse1":"6 avenue Cyrille Besset","cbAdresse2":"Le Virginia II","cbCp":"6800","cbVille":"CAGNES SUR MER","spLibelle1":"","spLibelle2":"","acDateSerment":"","coordinates":[7.1627036,43.6589848]},{"NomBarreau":"GRASSE","avNom":"FLORES","avPrenom":"Mandy","cbRaisonSociale":"FLORES MANDY","cbSiretSiren":"847913449","cbAdresse1":"1 Avenue de Verdun","cbAdresse2":"Résidence L'Athéna","cbCp":"6800","cbVille":"CAGNES SUR MER","spLibelle1":"","spLibelle2":"","acDateSerment":"","coordinates":[7.1486566,43.6622562]},{"NomBarreau":"GRASSE","avNom":"GISBERT","avPrenom":"Gaelle","cbRaisonSociale":"GISBERT GAELLE","cbSiretSiren":"518066634","cbAdresse1":"8 Cours du 11 Novembre","cbAdresse2":"Le Central Plaza Batiment D","cbCp":"6800","cbVille":"CAGNES SUR MER","spLibelle1":"","spLibelle2":"","acDateSerment":"","coordinates":[7.1497131,43.6616545]},{"NomBarreau":"GRASSE","avNom":"GORTINA","avPrenom":"Isabelle","cbRaisonSociale":"GORTINA ISABELLE","cbSiretSiren":"434957593","cbAdresse1":"91 avenue Cyrille Besset","cbAdresse2":"","cbCp":"6800","cbVille":"CAGNES SUR MER","spLibelle1":"","spLibelle2":"","acDateSerment":"","coordinates":[7.1627036,43.6589848]},{"NomBarreau":"GRASSE","avNom":"GUILLOT","avPrenom":"Gérald","cbRaisonSociale":"GUILLOT GERALD","cbSiretSiren":"480642933","cbAdresse1":"53 avenue des Alpes","cbAdresse2":"Le Saint-Jacques - Bat B","cbCp":"6800","cbVille":"CAGNES SUR MER","spLibelle1":"","spLibelle2":"","acDateSerment":"","coordinates":[7.1471906,43.6595705]},{"NomBarreau":"GRASSE","avNom":"GUYOT","avPrenom":"Dominique","cbRaisonSociale":"GUYOT DOMINIQUE","cbSiretSiren":"401174826","cbAdresse1":"9 boulevard Kennedy","cbAdresse2":"L'Ascot A","cbCp":"6800","cbVille":"CAGNES SUR MER","spLibelle1":"","spLibelle2":"","acDateSerment":"","coordinates":[7.1520275,43.6506782]},{"NomBarreau":"GRASSE","avNom":"KAUFFMANN","avPrenom":"Frédéric","cbRaisonSociale":"KAUFFMANN FREDERIC","cbSiretSiren":"539796680","cbAdresse1":"9 rue Bonaparte","cbAdresse2":"Le Manhattan","cbCp":"6800","cbVille":"CAGNES SUR MER","spLibelle1":"","spLibelle2":"","acDateSerment":"","coordinates":[7.1500902,43.6600535]},{"NomBarreau":"GRASSE","avNom":"LAFONT","avPrenom":"Caroline","cbRaisonSociale":"LAFONT CAROLINE","cbSiretSiren":"322194663","cbAdresse1":"6 chemin de la Minoterie","cbAdresse2":"Le Bagatelle","cbCp":"6800","cbVille":"CAGNES SUR MER","spLibelle1":"","spLibelle2":"","acDateSerment":"","coordinates":[7.148913,43.658009]},{"NomBarreau":"GRASSE","avNom":"LARRIBEAU","avPrenom":"Hadrien","cbRaisonSociale":"DELAGE - DAN - LARRIBEAU - RENAUDOT","cbSiretSiren":"444784045","cbAdresse1":"19 avenue Auguste Renoir","cbAdresse2":"","cbCp":"6800","cbVille":"CAGNES SUR MER","spLibelle1":"","spLibelle2":"","acDateSerment":"","coordinates":[7.1537511,43.6651539]},{"NomBarreau":"GRASSE","avNom":"LUCIANI","avPrenom":"Pascal-Alexis","cbRaisonSociale":"LUCIANI PASCAL-ALEXIS","cbSiretSiren":"338506645","cbAdresse1":"9 rue Bonaparte","cbAdresse2":"Le Manhattan","cbCp":"6800","cbVille":"CAGNES SUR MER","spLibelle1":"","spLibelle2":"","acDateSerment":"","coordinates":[7.1500902,43.6600535]},{"NomBarreau":"GRASSE","avNom":"MARTEL","avPrenom":"Pierre","cbRaisonSociale":"MARTEL PIERRE","cbSiretSiren":"417760287","cbAdresse1":"29 boulevard Kennedy","cbAdresse2":"L'Auteuil","cbCp":"6800","cbVille":"CAGNES SUR MER","spLibelle1":"Droit fiscal et droit douanier","spLibelle2":"","acDateSerment":"","coordinates":[7.1520721,43.6518163]},{"NomBarreau":"GRASSE","avNom":"MERASLI","avPrenom":"Karine","cbRaisonSociale":"MERASLI KARINE","cbSiretSiren":"824487912","cbAdresse1":"8 Cours du 11 Novembre","cbAdresse2":"Le Central Plaza","cbCp":"6800","cbVille":"CAGNES SUR MER","spLibelle1":"","spLibelle2":"","acDateSerment":"","coordinates":[7.1497131,43.6616545]},{"NomBarreau":"GRASSE","avNom":"PAOLETTI","avPrenom":"Grégory","cbRaisonSociale":"VALENTINI & PAOLETTI","cbSiretSiren":"821209558","cbAdresse1":"1 Avenue de Verdun","cbAdresse2":"Résidence L'Athéna","cbCp":"6800","cbVille":"CAGNES SUR MER","spLibelle1":"","spLibelle2":"","acDateSerment":"","coordinates":[7.1486566,43.6622562]},{"NomBarreau":"GRASSE","avNom":"PASTORINO","avPrenom":"Christophe","cbRaisonSociale":"PASTORINO CHRISTOPHE","cbSiretSiren":"749834792","cbAdresse1":"6 chemin de la Minoterie","cbAdresse2":"Le Bagatelle","cbCp":"6800","cbVille":"CAGNES SUR MER","spLibelle1":"","spLibelle2":"","acDateSerment":"","coordinates":[7.148913,43.658009]},{"NomBarreau":"GRASSE","avNom":"PIGET","avPrenom":"Marianne","cbRaisonSociale":"PIGET MARIANNE","cbSiretSiren":"377699509","cbAdresse1":"15 Avenue Auguste Renoir","cbAdresse2":"Le Verdun","cbCp":"6801","cbVille":"CAGNES SUR MER","spLibelle1":"","spLibelle2":"","acDateSerment":"","coordinates":[7.1537511,43.6651539]},{"NomBarreau":"GRASSE","avNom":"POULAIN","avPrenom":"Céline","cbRaisonSociale":"POULAIN CELINE","cbSiretSiren":"417591104","cbAdresse1":"80 avenue de Nice","cbAdresse2":"Le Flamboyant","cbCp":"6800","cbVille":"CAGNES SUR MER","spLibelle1":"","spLibelle2":"","acDateSerment":"","coordinates":[7.1773215,43.6605767]},{"NomBarreau":"GRASSE","avNom":"RENAUDOT","avPrenom":"Paul","cbRaisonSociale":"DELAGE - DAN - LARRIBEAU - RENAUDOT","cbSiretSiren":"444784045","cbAdresse1":"19 avenue Auguste Renoir","cbAdresse2":"","cbCp":"6800","cbVille":"CAGNES SUR MER","spLibelle1":"","spLibelle2":"","acDateSerment":"","coordinates":[7.1537511,43.6651539]},{"NomBarreau":"GRASSE","avNom":"SCHREYER","avPrenom":"Michaela","cbRaisonSociale":"SCHREYER MICHAELA","cbSiretSiren":"410709703","cbAdresse1":"6 avenue Cyrille BESSET","cbAdresse2":"Le Virginia II","cbCp":"6800","cbVille":"CAGNES SUR MER","spLibelle1":"","spLibelle2":"","acDateSerment":"","coordinates":[7.1627036,43.6589848]},{"NomBarreau":"GRASSE","avNom":"SCHUFFENECKER","avPrenom":"Thierry","cbRaisonSociale":"SCHUFFENECKER THIERRY","cbSiretSiren":"417700044","cbAdresse1":"120 chemin de la Maure","cbAdresse2":"","cbCp":"6800","cbVille":"CAGNES SUR MER","spLibelle1":"","spLibelle2":"","acDateSerment":"","coordinates":[7.1598989,43.6800597]},{"NomBarreau":"GRASSE","avNom":"TERESI","avPrenom":"Laure","cbRaisonSociale":"CARRION-TAMIOTTI - TERESI","cbSiretSiren":"522671437","cbAdresse1":"1 rue Modigliani","cbAdresse2":"","cbCp":"6800","cbVille":"CAGNES SUR MER","spLibelle1":"","spLibelle2":"","acDateSerment":"","coordinates":[7.1521049,43.6651327]},{"NomBarreau":"GRASSE","avNom":"TIQUET-MILLION","avPrenom":"Evelyne","cbRaisonSociale":"TIQUET-MILLION EVELYNE","cbSiretSiren":"434569273","cbAdresse1":"8 place de Gaulle","cbAdresse2":"Le Paris","cbCp":"6800","cbVille":"CAGNES SUR MER","spLibelle1":"","spLibelle2":"","acDateSerment":"","coordinates":[7.1503884,43.6639415]},{"NomBarreau":"GRASSE","avNom":"VALENTINI","avPrenom":"Walter","cbRaisonSociale":"VALENTINI & PAOLETTI","cbSiretSiren":"821209558","cbAdresse1":"1 Avenue de Verdun","cbAdresse2":"Résidence L'Athéna","cbCp":"6800","cbVille":"CAGNES SUR MER","spLibelle1":"","spLibelle2":"","acDateSerment":"","coordinates":[7.1486566,43.6622562]},{"NomBarreau":"GRASSE","avNom":"VERIGNON","avPrenom":"Benoit","cbRaisonSociale":"VERIGNON","cbSiretSiren":"840638456","cbAdresse1":"8 Place de Gaulle","cbAdresse2":"Le Paris","cbCp":"6800","cbVille":"CAGNES SUR MER","spLibelle1":"","spLibelle2":"","acDateSerment":"","coordinates":[7.1503884,43.6639415]}]