[{"NomBarreau":"AIN","avNom":"ACHEB","avPrenom":"Hanane","cbRaisonSociale":"ACHEB AVOCATS & ASSOCIES","cbSiretSiren":"913668232","cbAdresse1":"12 RUE DE GENEVE","cbAdresse2":"","cbCp":"1210","cbVille":"FERNEY VOLTAIRE","spLibelle1":"","spLibelle2":"","acDateSerment":"","coordinates":[6.111420033049129,46.2550312]},{"NomBarreau":"AIN","avNom":"BACHMANN","avPrenom":"Adrien","cbRaisonSociale":"BACHMANN ADRIEN","cbSiretSiren":"920591484","cbAdresse1":"13A CHEMIN DU LEVANT","cbAdresse2":"LE KEYNES","cbCp":"1210","cbVille":"FERNEY VOLTAIRE","spLibelle1":"","spLibelle2":"","acDateSerment":"","coordinates":[6.113499495724696,46.26084]},{"NomBarreau":"AIN","avNom":"DEVEAUX","avPrenom":"Emmanuelle","cbRaisonSociale":"DEVEAUX EMMANUELLE","cbSiretSiren":"441837127","cbAdresse1":"13 Chemin du Levant","cbAdresse2":"Immeuble Jean Baptiste Say","cbCp":"1210","cbVille":"FERNEY VOLTAIRE","spLibelle1":"","spLibelle2":"","acDateSerment":"","coordinates":[6.1141041,46.260765]},{"NomBarreau":"AIN","avNom":"DUBOULOZ","avPrenom":"Nathalie","cbRaisonSociale":"NATHALIE DUBOULOZ","cbSiretSiren":"495100935","cbAdresse1":"13 B Chemin du Levant","cbAdresse2":"Immeuble JB Say","cbCp":"1210","cbVille":"FERNEY VOLTAIRE","spLibelle1":"","spLibelle2":"","acDateSerment":"","coordinates":[6.1141041,46.260765]},{"NomBarreau":"AIN","avNom":"SIMORRE","avPrenom":"Peggy","cbRaisonSociale":"SIMORRE PEGGY","cbSiretSiren":"839631090","cbAdresse1":"13B CHEMIN DU LEVANT","cbAdresse2":"IMMEUBLE JB SAY","cbCp":"1210","cbVille":"FERNEY VOLTAIRE","spLibelle1":"","spLibelle2":"","acDateSerment":"","coordinates":[6.1141041,46.260765]},{"NomBarreau":"AIN","avNom":"TOUBKIN","avPrenom":"Nathalie","cbRaisonSociale":"TOUBKIN NATHALIE","cbSiretSiren":"531212165","cbAdresse1":"13B CHEMIN DU LEVANT","cbAdresse2":"IMMEUBLE JB SAY","cbCp":"1210","cbVille":"FERNEY VOLTAIRE","spLibelle1":"","spLibelle2":"","acDateSerment":"","coordinates":[6.1141041,46.260765]},{"NomBarreau":"AIN","avNom":"VIANES","avPrenom":"Elena","cbRaisonSociale":"VIANES ELENA","cbSiretSiren":"801275124","cbAdresse1":"36 Grand Rue","cbAdresse2":"","cbCp":"1210","cbVille":"FERNEY VOLTAIRE","spLibelle1":"","spLibelle2":"","acDateSerment":"","coordinates":[6.1086907,46.2576841]},{"NomBarreau":"AIN","avNom":"VIGUIER","avPrenom":"Damien","cbRaisonSociale":"VIGUIER DAMIEN","cbSiretSiren":"529703456","cbAdresse1":"13 B Chemin du Levant","cbAdresse2":"Immeuble Jean-Baptise SAY","cbCp":"1210","cbVille":"FERNEY VOLTAIRE","spLibelle1":"","spLibelle2":"","acDateSerment":"","coordinates":[6.1141041,46.260765]}]