[{"NomBarreau":"LYON","avNom":"BALSA","avPrenom":"Romain","cbRaisonSociale":"BALSA ROMAIN","cbSiretSiren":"797575040","cbAdresse1":"1 rue des Vergers","cbAdresse2":"","cbCp":"69760","cbVille":"LIMONEST","spLibelle1":"","spLibelle2":"","acDateSerment":"","coordinates":[4.7715409,45.806881]},{"NomBarreau":"LYON","avNom":"MONNIER-HAUSER","avPrenom":"Aline","cbRaisonSociale":"AMH AVOCAT","cbSiretSiren":"810488197","cbAdresse1":"1, rue des Vergers","cbAdresse2":"Parc d'Affaires SWEN PARC","cbCp":"69760","cbVille":"LIMONEST","spLibelle1":"","spLibelle2":"","acDateSerment":"","coordinates":[4.7715409,45.806881]}]