[{"NomBarreau":"CAEN","avNom":"BOUTHORS","avPrenom":"Vanessa","cbRaisonSociale":"L.B.C.L","cbSiretSiren":"828051367","cbAdresse1":"7 Rue Chapron","cbAdresse2":"","cbCp":"14120","cbVille":"MONDEVILLE","spLibelle1":"","spLibelle2":"","acDateSerment":"","coordinates":[-0.3195944,49.1776507]},{"NomBarreau":"CAEN","avNom":"LECLERC","avPrenom":"Thomas","cbRaisonSociale":"L.B.C.L","cbSiretSiren":"828051367","cbAdresse1":"7 Rue Chapron","cbAdresse2":"","cbCp":"14120","cbVille":"MONDEVILLE","spLibelle1":"","spLibelle2":"","acDateSerment":"","coordinates":[-0.3195944,49.1776507]},{"NomBarreau":"CAEN","avNom":"MONTI","avPrenom":"Sandrine","cbRaisonSociale":"MONTI SANDRINE","cbSiretSiren":"791195092","cbAdresse1":"9E Rue Chapron","cbAdresse2":"","cbCp":"14120","cbVille":"MONDEVILLE","spLibelle1":"","spLibelle2":"","acDateSerment":"","coordinates":[-0.3195944,49.1776507]}]