[{"NomBarreau":"MEAUX","avNom":"CLAUDET","avPrenom":"Emeraude","cbRaisonSociale":"CLAUDET EMERAUDE","cbSiretSiren":"903521631","cbAdresse1":"14 Avenue de l'Europe","cbAdresse2":"","cbCp":"77144","cbVille":"MONTEVRAIN","spLibelle1":"","spLibelle2":"","acDateSerment":"","coordinates":[2.7642428,48.8528826]},{"NomBarreau":"MEAUX","avNom":"RABIER","avPrenom":"Emmanuel","cbRaisonSociale":"RABIER-NETTHAVONGS","cbSiretSiren":"813754306","cbAdresse1":"14 Avenue de l'Europe","cbAdresse2":"","cbCp":"77144","cbVille":"MONTEVRAIN","spLibelle1":"","spLibelle2":"","acDateSerment":"","coordinates":[2.7642428,48.8528826]}]